life_line_chart/AncestorChart.py
life_line_chart/AncestorChartStrings.json
life_line_chart/BaseChart.py
life_line_chart/BaseChartStrings.json
life_line_chart/BaseFamily.py
life_line_chart/BaseIndividual.py
life_line_chart/BaseSVGChart.py
life_line_chart/DescendantChart.py
life_line_chart/DescendantChartStrings.json
life_line_chart/Exceptions.py
life_line_chart/GedcomFamily.py
life_line_chart/GedcomIndividual.py
life_line_chart/GedcomInstanceContainer.py
life_line_chart/GedcomParsing.py
life_line_chart/GraphicalFamily.py
life_line_chart/GraphicalIndividual.py
life_line_chart/InstanceContainer.py
life_line_chart/IntermediateGraphicalItems.py
life_line_chart/MarkdownParser.py
life_line_chart/ReadGedcom.py
life_line_chart/SimpleSVGItems.py
life_line_chart/Translation.py
life_line_chart/__init__.py
life_line_chart/_autogenerate_data.py
life_line_chart/_version.py
life_line_chart/ringe.png
life_line_chart-1.7.7.data/data/life_line_chart/AncestorChartStrings.json
life_line_chart-1.7.7.data/data/life_line_chart/BaseChartStrings.json
life_line_chart-1.7.7.data/data/life_line_chart/DescendantChartStrings.json
life_line_chart-1.7.7.data/data/life_line_chart/ringe.png
life_line_chart-1.7.7.dist-info/LICENSE
life_line_chart-1.7.7.dist-info/METADATA
life_line_chart-1.7.7.dist-info/WHEEL
life_line_chart-1.7.7.dist-info/top_level.txt
life_line_chart-1.7.7.dist-info/RECORD
