Metadata-Version: 2.1
Name: life-line-chart
Version: 1.7.7
Summary: Generate ancestor (genealogy) chart
Home-page: https://github.com/CWSchulze/life_line_chart
Author: Christian Schulze
Author-email: c.w.schulze@gmail.com
License: MIT License
Keywords: genealogy,gedcom,chart,ancestors
Platform: OS Independent
Classifier: Programming Language :: Python :: 3
Classifier: Intended Audience :: Developers
Classifier: License :: OSI Approved :: MIT License
Classifier: Development Status :: 4 - Beta
Classifier: Natural Language :: English
Classifier: Topic :: Scientific/Engineering
Classifier: Topic :: Scientific/Engineering :: Information Analysis
Classifier: Topic :: Scientific/Engineering :: Visualization
Classifier: Topic :: Software Development :: Libraries :: Python Modules
License-File: LICENSE
Requires-Dist: svgwrite
Provides-Extra: data_generator
Requires-Dist: names ; extra == 'data_generator'
Provides-Extra: photo_tests
Requires-Dist: pillow ; extra == 'photo_tests'
